<?xml version="1.0" encoding="UTF-8"?>
<!DOCTYPE struts-config PUBLIC "-//Apache Software Foundation//DTD Struts Configuration 1.2//EN" "http://jakarta.apache.org/struts/dtds/struts-config_1_2.dtd">
<struts-config>
  <form-beans>
    <form-bean name="addressForm" type="examples.app1.AddressForm" />
  </form-beans>
  <global-forwards>
    <forward contextRelative="true" name="editAddressSrcJsp" path="/examples/struts_app1/edit-addressjsp.txt" />
    <forward contextRelative="true" name="showAddressSrcJsp" path="/examples/struts_app1/show-addressjsp.txt" />
    <forward contextRelative="true" name="editAddressSrc" path="/examples/struts_app1/edit-address.txt" />
    <forward contextRelative="true" name="showAddressSrc" path="/examples/struts_app1/show-address.txt" />
  </global-forwards>
  <action-mappings>
    <action name="addressForm" path="/address1" scope="request" type="examples.app1.AddressAction">
      <forward contextRelative="true" name="showAddress" path="/examples/struts_app1/show-address.jsp" />
      <forward contextRelative="true" name="editAddress" path="/examples/struts_app1/edit-address.jsp" />
    </action>
    <action name="addressForm" path="/address2" scope="request" type="examples.app1.AddressAction">
      <forward contextRelative="true" name="showAddress" path="/examples/struts_app1/show-address.vm" />
      <forward contextRelative="true" name="editAddress" path="/examples/struts_app1/edit-address.vm" />
    </action>
  </action-mappings>
  <message-resources parameter="examples.app1.ApplicationResources" />
  <plug-in className="org.apache.struts.validator.ValidatorPlugIn">
    <set-property property="pathnames" value="/WEB-INF/validator-rules.xml,/WEB-INF/validation.xml" />
  </plug-in>
</struts-config>
